LICENSE
MANIFEST.in
setup.py
sheetgen/__init__.py
sheetgen/main.py
sheetgen.egg-info/PKG-INFO
sheetgen.egg-info/SOURCES.txt
sheetgen.egg-info/dependency_links.txt
sheetgen.egg-info/entry_points.txt
sheetgen.egg-info/not-zip-safe
sheetgen.egg-info/top_level.txt
sheetgen/templates/.DS_Store
sheetgen/templates/sheet.html