Metadata-Version: 1.0
Name: sheetgen
Version: 1.0.0
Summary: Generating of EAN codesheets made easy.
Home-page: https://github.com/uppsaladatavetare/codesheet-generator
Author: Krzysztof Jagiello
Author-email: me@kjagiello.com
License: MIT license
Platform: UNKNOWN
